broker/ApiBase.py
broker/Client.py
broker/__init__.py
broker/ameritrade_api.py
broker/ameritrade_url.py
broker/api_base.py
broker/paper_trade.py
broker/robinhood.py
broker/robinhood_api.py
broker/robinhood_url.py
sample/BookAnalysis.py
sample/Notes.py
sample/__init__.py
sample/paper_trading.py
test/__init__.py
py_broker-1.0.1.dist-info/LICENSE
py_broker-1.0.1.dist-info/METADATA
py_broker-1.0.1.dist-info/WHEEL
py_broker-1.0.1.dist-info/top_level.txt
py_broker-1.0.1.dist-info/RECORD
