Metadata-Version: 2.1
Name: py-broker
Version: 1.0.1
Summary: Python client for stock trading broker APIs
Home-page: https://github.com/ilemus/Robinhood
Author: Isaac Lemus
Author-email: ilemus@umich.edu
License: UNKNOWN
Platform: UNKNOWN
Classifier: Programming Language :: Python :: 3
Classifier: License :: OSI Approved :: GNU General Public License v3 (GPLv3)
Classifier: Operating System :: OS Independent
Requires-Python: >=3.6
